[
  {
    "command": "title",
    "category": 1,
    "args": [
      " "
    ],
    "number": 0
  },
  {
    "command": "outline",
    "category": 1,
    "args": [
      " "
    ],
    "number": 1
  },
  {
    "command": "chara_full",
    "category": 1,
    "args": [
      "111711",
      "LC",
      "6"
    ],
    "number": 68
  },
  {
    "command": "chara_full",
    "category": 1,
    "args": [
      "111511",
      "RC",
      "6"
    ],
    "number": 68
  },
  {
    "command": "fadein_all",
    "category": 1,
    "args": [
      "30"
    ],
    "number": 84
  },
  {
    "command": "window_visible",
    "category": 1,
    "args": [
      "true"
    ],
    "number": 41
  },
  {
    "command": "focus",
    "category": 1,
    "args": [
      "111711"
    ],
    "number": 4
  },
  {
    "command": "bust",
    "category": 1,
    "args": [
      "111711",
      "0"
    ],
    "number": 50
  },
  {
    "command": "vo",
    "category": 1,
    "args": [
      "vo_adv_5029321_000"
    ],
    "number": 12
  },
  {
    "command": "face",
    "category": 1,
    "args": [
      "111711",
      "6"
    ],
    "number": 3
  },
  {
    "command": "emotion",
    "category": 3,
    "args": [
      "notice1_L",
      "111711",
      "-35",
      "555",
      "se_adv_emote_common_01"
    ],
    "number": 59
  },
  {
    "command": "print",
    "category": 1,
    "args": [
      "伊莉亞",
      "怎麼回事？"
    ],
    "number": 6
  },
  {
    "command": "wait",
    "category": 1,
    "args": [
      "30"
    ],
    "number": 13
  },
  {
    "command": "print",
    "category": 1,
    "args": [
      "伊莉亞",
      "這些馴鹿，"
    ],
    "number": 6
  },
  {
    "command": "wait",
    "category": 1,
    "args": [
      "30"
    ],
    "number": 13
  },
  {
    "command": "print",
    "category": 1,
    "args": [
      "伊莉亞",
      "從袋子裡拿出什麼來了！"
    ],
    "number": 6
  },
  {
    "command": "wait",
    "category": 1,
    "args": [
      "80"
    ],
    "number": 13
  },
  {
    "command": "print",
    "category": 1,
    "args": [
      "伊莉亞",
      "\n和咱們長得一模一樣的人\u2026\u2026"
    ],
    "number": 6
  },
  {
    "command": "wait",
    "category": 1,
    "args": [
      "60"
    ],
    "number": 13
  },
  {
    "command": "face",
    "category": 1,
    "args": [
      "111711",
      "4"
    ],
    "number": 3
  },
  {
    "command": "print",
    "category": 1,
    "args": [
      "伊莉亞",
      "牠們到底做何打算？"
    ],
    "number": 6
  },
  {
    "command": "touch",
    "category": 1,
    "args": [],
    "number": 10
  },
  {
    "command": "focus",
    "category": 1,
    "args": [
      "111511"
    ],
    "number": 4
  },
  {
    "command": "bust",
    "category": 1,
    "args": [
      "111511",
      "0"
    ],
    "number": 50
  },
  {
    "command": "vo",
    "category": 1,
    "args": [
      "vo_adv_5029321_001"
    ],
    "number": 12
  },
  {
    "command": "face",
    "category": 1,
    "args": [
      "111511",
      "1"
    ],
    "number": 3
  },
  {
    "command": "print",
    "category": 1,
    "args": [
      "克莉絲提娜",
      "喔？"
    ],
    "number": 6
  },
  {
    "command": "wait",
    "category": 1,
    "args": [
      "30"
    ],
    "number": 13
  },
  {
    "command": "print",
    "category": 1,
    "args": [
      "克莉絲提娜",
      "有意思！"
    ],
    "number": 6
  },
  {
    "command": "wait",
    "category": 1,
    "args": [
      "40"
    ],
    "number": 13
  },
  {
    "command": "print",
    "category": 1,
    "args": [
      "克莉絲提娜",
      "\n這裡竟然同時存在著兩個克莉絲提娜\u2026\u2026"
    ],
    "number": 6
  },
  {
    "command": "wait",
    "category": 1,
    "args": [
      "60"
    ],
    "number": 13
  },
  {
    "command": "print",
    "category": 1,
    "args": [
      "克莉絲提娜",
      "看來會是一場愉快的盛宴了\u266A"
    ],
    "number": 6
  },
  {
    "command": "wait",
    "category": 1,
    "args": [
      "50"
    ],
    "number": 13
  },
  {
    "command": "print",
    "category": 1,
    "args": [
      "克莉絲提娜",
      "\n"
    ],
    "number": 6
  },
  {
    "command": "face",
    "category": 1,
    "args": [
      "111511",
      "2"
    ],
    "number": 3
  },
  {
    "command": "print",
    "category": 1,
    "args": [
      "克莉絲提娜",
      "妳可別讓我失望啊？"
    ],
    "number": 6
  },
  {
    "command": "wait",
    "category": 1,
    "args": [
      "30"
    ],
    "number": 13
  },
  {
    "command": "print",
    "category": 1,
    "args": [
      "克莉絲提娜",
      "\u3000另一個我啊。"
    ],
    "number": 6
  },
  {
    "command": "touch",
    "category": 1,
    "args": [],
    "number": 10
  },
  {
    "command": "window_visible",
    "category": 1,
    "args": [
      "false"
    ],
    "number": 41
  },
  {
    "command": "fadeout_all",
    "category": 2,
    "args": [
      "30"
    ],
    "number": 45
  },
  {
    "command": "chara_full",
    "category": 1,
    "args": [
      "111611",
      "C",
      "3"
    ],
    "number": 68
  },
  {
    "command": "fadein",
    "category": 2,
    "args": [
      "111611",
      "30"
    ],
    "number": 18
  },
  {
    "command": "window_visible",
    "category": 1,
    "args": [
      "true"
    ],
    "number": 41
  },
  {
    "command": "focus",
    "category": 1,
    "args": [
      "111611"
    ],
    "number": 4
  },
  {
    "command": "bust",
    "category": 1,
    "args": [
      "111611",
      "0"
    ],
    "number": 50
  },
  {
    "command": "vo",
    "category": 1,
    "args": [
      "vo_adv_5029321_002"
    ],
    "number": 12
  },
  {
    "command": "face",
    "category": 1,
    "args": [
      "111611",
      "3"
    ],
    "number": 3
  },
  {
    "command": "print",
    "category": 1,
    "args": [
      "望",
      "不論外表再怎麼相似，"
    ],
    "number": 6
  },
  {
    "command": "wait",
    "category": 1,
    "args": [
      "50"
    ],
    "number": 13
  },
  {
    "command": "print",
    "category": 1,
    "args": [
      "望",
      "妳都不可能模仿得了我的唷？"
    ],
    "number": 6
  },
  {
    "command": "wait",
    "category": 1,
    "args": [
      "40"
    ],
    "number": 13
  },
  {
    "command": "print",
    "category": 1,
    "args": [
      "望",
      "\n"
    ],
    "number": 6
  },
  {
    "command": "nod",
    "category": 2,
    "args": [
      "111611"
    ],
    "number": 25
  },
  {
    "command": "print",
    "category": 1,
    "args": [
      "望",
      "我要讓妳看看，"
    ],
    "number": 6
  },
  {
    "command": "wait",
    "category": 1,
    "args": [
      "30"
    ],
    "number": 13
  },
  {
    "command": "print",
    "category": 1,
    "args": [
      "望",
      "真正的偶像才有的光芒！"
    ],
    "number": 6
  },
  {
    "command": "touch",
    "category": 1,
    "args": [],
    "number": 10
  },
  {
    "command": "window_visible",
    "category": 1,
    "args": [
      "false"
    ],
    "number": 41
  },
  {
    "command": "fadeout",
    "category": 2,
    "args": [
      "111611",
      "30"
    ],
    "number": 19
  },
  {
    "command": "chara_full",
    "category": 1,
    "args": [
      "111711",
      "LC",
      "1"
    ],
    "number": 68
  },
  {
    "command": "chara_full",
    "category": 1,
    "args": [
      "111511",
      "RC",
      "1"
    ],
    "number": 68
  },
  {
    "command": "fadein_all",
    "category": 1,
    "args": [
      "30"
    ],
    "number": 84
  },
  {
    "command": "window_visible",
    "category": 1,
    "args": [
      "true"
    ],
    "number": 41
  },
  {
    "command": "focus",
    "category": 1,
    "args": [
      "111711"
    ],
    "number": 4
  },
  {
    "command": "bust",
    "category": 1,
    "args": [
      "111711",
      "0"
    ],
    "number": 50
  },
  {
    "command": "vo",
    "category": 1,
    "args": [
      "vo_adv_5029321_003"
    ],
    "number": 12
  },
  {
    "command": "face",
    "category": 1,
    "args": [
      "111711",
      "1"
    ],
    "number": 3
  },
  {
    "command": "print",
    "category": 1,
    "args": [
      "伊莉亞",
      "統御黑夜之人，有妾身一個人就夠了。"
    ],
    "number": 6
  },
  {
    "command": "wait",
    "category": 1,
    "args": [
      "60"
    ],
    "number": 13
  },
  {
    "command": "print",
    "category": 1,
    "args": [
      "伊莉亞",
      "\n"
    ],
    "number": 6
  },
  {
    "command": "face",
    "category": 1,
    "args": [
      "111711",
      "3"
    ],
    "number": 3
  },
  {
    "command": "print",
    "category": 1,
    "args": [
      "伊莉亞",
      "讓妳見識一下妾身與你之間的差距吧！"
    ],
    "number": 6
  },
  {
    "command": "touch",
    "category": 1,
    "args": [],
    "number": 10
  },
  {
    "command": "focus",
    "category": 1,
    "args": [
      "111511"
    ],
    "number": 4
  },
  {
    "command": "bust",
    "category": 1,
    "args": [
      "111511",
      "0"
    ],
    "number": 50
  },
  {
    "command": "vo",
    "category": 1,
    "args": [
      "vo_adv_5029321_004"
    ],
    "number": 12
  },
  {
    "command": "face",
    "category": 1,
    "args": [
      "111511",
      "1"
    ],
    "number": 3
  },
  {
    "command": "nod",
    "category": 2,
    "args": [
      "111511"
    ],
    "number": 25
  },
  {
    "command": "print",
    "category": 1,
    "args": [
      "克莉絲提娜",
      "來吧！"
    ],
    "number": 6
  },
  {
    "command": "wait",
    "category": 1,
    "args": [
      "20"
    ],
    "number": 13
  },
  {
    "command": "print",
    "category": 1,
    "args": [
      "克莉絲提娜",
      "贗品們！"
    ],
    "number": 6
  },
  {
    "command": "wait",
    "category": 1,
    "args": [
      "25"
    ],
    "number": 13
  },
  {
    "command": "print",
    "category": 1,
    "args": [
      "克莉絲提娜",
      "\n有本事就打倒我們、"
    ],
    "number": 6
  },
  {
    "command": "wait",
    "category": 1,
    "args": [
      "30"
    ],
    "number": 13
  },
  {
    "command": "print",
    "category": 1,
    "args": [
      "克莉絲提娜",
      "進而取代吧！"
    ],
    "number": 6
  },
  {
    "command": "wait",
    "category": 1,
    "args": [
      "40"
    ],
    "number": 13
  },
  {
    "command": "print",
    "category": 1,
    "args": [
      "克莉絲提娜",
      "\n"
    ],
    "number": 6
  },
  {
    "command": "face",
    "category": 1,
    "args": [
      "111511",
      "2"
    ],
    "number": 3
  },
  {
    "command": "print",
    "category": 1,
    "args": [
      "克莉絲提娜",
      "啊哈哈！"
    ],
    "number": 6
  },
  {
    "command": "wait",
    "category": 1,
    "args": [
      "30"
    ],
    "number": 13
  },
  {
    "command": "print",
    "category": 1,
    "args": [
      "克莉絲提娜",
      "真正的克莉絲提娜可不好對付喔？"
    ],
    "number": 6
  },
  {
    "command": "touch",
    "category": 1,
    "args": [],
    "number": 10
  },
  {
    "command": "window_visible",
    "category": 1,
    "args": [
      "false"
    ],
    "number": 41
  },
  {
    "command": "fadeout_all",
    "category": 2,
    "args": [
      "30"
    ],
    "number": 45
  },
  {
    "command": "chara_full",
    "category": 1,
    "args": [
      "111611",
      "C",
      "4"
    ],
    "number": 68
  },
  {
    "command": "fadein",
    "category": 2,
    "args": [
      "111611",
      "30"
    ],
    "number": 18
  },
  {
    "command": "window_visible",
    "category": 1,
    "args": [
      "true"
    ],
    "number": 41
  },
  {
    "command": "focus",
    "category": 1,
    "args": [
      "111611"
    ],
    "number": 4
  },
  {
    "command": "bust",
    "category": 1,
    "args": [
      "111611",
      "0"
    ],
    "number": 50
  },
  {
    "command": "vo",
    "category": 1,
    "args": [
      "vo_adv_5029321_005"
    ],
    "number": 12
  },
  {
    "command": "face",
    "category": 1,
    "args": [
      "111611",
      "4"
    ],
    "number": 3
  },
  {
    "command": "emotion",
    "category": 3,
    "args": [
      "sweat2_R",
      "111611",
      "65",
      "530",
      "se_adv_emote_sweat_02"
    ],
    "number": 59
  },
  {
    "command": "print",
    "category": 1,
    "args": [
      "望",
      "製作人！"
    ],
    "number": 6
  },
  {
    "command": "wait",
    "category": 1,
    "args": [
      "20"
    ],
    "number": 13
  },
  {
    "command": "print",
    "category": 1,
    "args": [
      "望",
      "\n妳這樣變得好像壞人一樣了！"
    ],
    "number": 6
  },
  {
    "command": "touch",
    "category": 1,
    "args": [],
    "number": 10
  },
  {
    "command": "window_visible",
    "category": 1,
    "args": [
      "false"
    ],
    "number": 41
  },
  {
    "command": "fadeout",
    "category": 2,
    "args": [
      "111611",
      "30"
    ],
    "number": 19
  }
]