[
  {
    "command": "title",
    "category": 1,
    "args": [
      "魔法提督ラブリー\u2605モニカ\u3000レッツゴー！マジカルカルテット！ 次回予告"
    ],
    "number": 0
  },
  {
    "command": "outline",
    "category": 1,
    "args": [
      "平和\u306A街\u306B巻\u304D起\u3053\u308B愛\u3068希望\u306E戦\u3044！\u3000大\u304D\u306A夢\u3092胸\u306B抱\u304D、今\u3053\u305D変身\u3060！\u3000魔法提督ラブリー\u2605モニカ\u304C指揮\u3092執\u308B！"
    ],
    "number": 1
  },
  {
    "command": "background",
    "category": 1,
    "args": [
      "500010"
    ],
    "number": 5
  },
  {
    "command": "amb",
    "category": 1,
    "args": [
      "amb_adv_town_day_01"
    ],
    "number": 51
  },
  {
    "command": "bg_pan",
    "category": 1,
    "args": [
      "-170",
      "0"
    ],
    "number": 86
  },
  {
    "command": "chara_full",
    "category": 1,
    "args": [
      "105311",
      "C",
      "1"
    ],
    "number": 68
  },
  {
    "command": "fadein",
    "category": 2,
    "args": [
      "105311",
      "30"
    ],
    "number": 18
  },
  {
    "command": "window_visible",
    "category": 1,
    "args": [
      "TRUE"
    ],
    "number": 41
  },
  {
    "command": "bgm",
    "category": 1,
    "args": [
      "bgm_M422",
      "0",
      "0",
      "1"
    ],
    "number": 9
  },
  {
    "command": "focus",
    "category": 1,
    "args": [
      "105311"
    ],
    "number": 4
  },
  {
    "command": "bust",
    "category": 1,
    "args": [
      "105311",
      "0"
    ],
    "number": 50
  },
  {
    "command": "vo",
    "category": 1,
    "args": [
      "vo_adv_5052101_000"
    ],
    "number": 12
  },
  {
    "command": "face",
    "category": 1,
    "args": [
      "105311",
      "1"
    ],
    "number": 3
  },
  {
    "command": "print",
    "category": 1,
    "args": [
      "モニカ",
      "私\u306F"
    ],
    "number": 6
  },
  {
    "command": "wait",
    "category": 1,
    "args": [
      "25"
    ],
    "number": 13
  },
  {
    "command": "print",
    "category": 1,
    "args": [
      "モニカ",
      "モニカ・ヴァイスヴィント！"
    ],
    "number": 6
  },
  {
    "command": "wait",
    "category": 1,
    "args": [
      "30"
    ],
    "number": 13
  },
  {
    "command": "print",
    "category": 1,
    "args": [
      "モニカ",
      "\n"
    ],
    "number": 6
  },
  {
    "command": "eye_open",
    "category": 1,
    "args": [
      "False"
    ],
    "number": 56
  },
  {
    "command": "print",
    "category": 1,
    "args": [
      "モニカ",
      "誇\u308A高\u304D"
    ],
    "number": 6
  },
  {
    "command": "wait",
    "category": 1,
    "args": [
      "25"
    ],
    "number": 13
  },
  {
    "command": "print",
    "category": 1,
    "args": [
      "モニカ",
      "ヴァイスフリューゲル\u306B所属\u3059\u308B、"
    ],
    "number": 6
  },
  {
    "command": "wait",
    "category": 1,
    "args": [
      "25"
    ],
    "number": 13
  },
  {
    "command": "print",
    "category": 1,
    "args": [
      "モニカ",
      "\n"
    ],
    "number": 6
  },
  {
    "command": "eye_open",
    "category": 1,
    "args": [
      "True"
    ],
    "number": 56
  },
  {
    "command": "print",
    "category": 1,
    "args": [
      "モニカ",
      "立派\u306A軍人\u3060！"
    ],
    "number": 6
  },
  {
    "command": "touch",
    "category": 1,
    "args": [],
    "number": 10
  },
  {
    "command": "focus",
    "category": 1,
    "args": [
      "105311"
    ],
    "number": 4
  },
  {
    "command": "bust",
    "category": 1,
    "args": [
      "105311",
      "0"
    ],
    "number": 50
  },
  {
    "command": "vo",
    "category": 1,
    "args": [
      "vo_adv_5052101_001"
    ],
    "number": 12
  },
  {
    "command": "face",
    "category": 1,
    "args": [
      "105311",
      "1"
    ],
    "number": 3
  },
  {
    "command": "nod",
    "category": 2,
    "args": [
      "105311"
    ],
    "number": 25
  },
  {
    "command": "se",
    "category": 1,
    "args": [
      "se_adv_stepadd_cloth_norm_01_move_01"
    ],
    "number": 26
  },
  {
    "command": "print",
    "category": 1,
    "args": [
      "モニカ",
      "私\u306B課\u305B\u3089\u308C\u305F責務\u306F、"
    ],
    "number": 6
  },
  {
    "command": "wait",
    "category": 1,
    "args": [
      "35"
    ],
    "number": 13
  },
  {
    "command": "print",
    "category": 1,
    "args": [
      "モニカ",
      "\n\u3053\u306E国\u306B関\u3059\u308B\u3053\u3068\u3092調査\u3057、"
    ],
    "number": 6
  },
  {
    "command": "wait",
    "category": 1,
    "args": [
      "40"
    ],
    "number": 13
  },
  {
    "command": "print",
    "category": 1,
    "args": [
      "モニカ",
      "祖国\u3078報告\u3059\u308B\u3068\u3044\u3046\u3082\u306E。"
    ],
    "number": 6
  },
  {
    "command": "touch",
    "category": 1,
    "args": [],
    "number": 10
  },
  {
    "command": "focus",
    "category": 1,
    "args": [
      "105311"
    ],
    "number": 4
  },
  {
    "command": "bust",
    "category": 1,
    "args": [
      "105311",
      "0"
    ],
    "number": 50
  },
  {
    "command": "vo",
    "category": 1,
    "args": [
      "vo_adv_5052101_002"
    ],
    "number": 12
  },
  {
    "command": "face",
    "category": 1,
    "args": [
      "105311",
      "1"
    ],
    "number": 3
  },
  {
    "command": "print",
    "category": 1,
    "args": [
      "モニカ",
      "\u305D\u306E重要\u306A責務\u3092果\u305F\u3059\u305F\u3081、"
    ],
    "number": 6
  },
  {
    "command": "wait",
    "category": 1,
    "args": [
      "50"
    ],
    "number": 13
  },
  {
    "command": "print",
    "category": 1,
    "args": [
      "モニカ",
      "\n【ヴァイスフリューゲル\u3000ランドソル支部】\u3092結成\u3057\u305F私\u306F、"
    ],
    "number": 6
  },
  {
    "command": "wait",
    "category": 1,
    "args": [
      "35"
    ],
    "number": 13
  },
  {
    "command": "print",
    "category": 1,
    "args": [
      "モニカ",
      "\n"
    ],
    "number": 6
  },
  {
    "command": "face",
    "category": 1,
    "args": [
      "105311",
      "2"
    ],
    "number": 3
  },
  {
    "command": "print",
    "category": 1,
    "args": [
      "モニカ",
      "日々、"
    ],
    "number": 6
  },
  {
    "command": "wait",
    "category": 1,
    "args": [
      "20"
    ],
    "number": 13
  },
  {
    "command": "print",
    "category": 1,
    "args": [
      "モニカ",
      "\u3053\u306E街\u3067大活躍\u3092繰\u308A広\u3052\u3066\u3044\u308B\u306E\u3067\u3042\u308B！"
    ],
    "number": 6
  },
  {
    "command": "touch",
    "category": 1,
    "args": [],
    "number": 10
  },
  {
    "command": "focus",
    "category": 1,
    "args": [
      "105311"
    ],
    "number": 4
  },
  {
    "command": "bust",
    "category": 1,
    "args": [
      "105311",
      "0"
    ],
    "number": 50
  },
  {
    "command": "vo",
    "category": 1,
    "args": [
      "vo_adv_5052101_003"
    ],
    "number": 12
  },
  {
    "command": "face",
    "category": 1,
    "args": [
      "105311",
      "1"
    ],
    "number": 3
  },
  {
    "command": "print",
    "category": 1,
    "args": [
      "モニカ",
      "\u305D\u3093\u306A私\u306E夢\u306F、"
    ],
    "number": 6
  },
  {
    "command": "wait",
    "category": 1,
    "args": [
      "35"
    ],
    "number": 13
  },
  {
    "command": "print",
    "category": 1,
    "args": [
      "モニカ",
      "\n立派\u306A軍人\u3068\u3057\u3066"
    ],
    "number": 6
  },
  {
    "command": "wait",
    "category": 1,
    "args": [
      "25"
    ],
    "number": 13
  },
  {
    "command": "print",
    "category": 1,
    "args": [
      "モニカ",
      "祖国\u306E役\u306B立\u3061、"
    ],
    "number": 6
  },
  {
    "command": "wait",
    "category": 1,
    "args": [
      "40"
    ],
    "number": 13
  },
  {
    "command": "print",
    "category": 1,
    "args": [
      "モニカ",
      "\n"
    ],
    "number": 6
  },
  {
    "command": "eye_open",
    "category": 1,
    "args": [
      "False"
    ],
    "number": 56
  },
  {
    "command": "print",
    "category": 1,
    "args": [
      "モニカ",
      "\u3086\u304F\u3086\u304F\u306F"
    ],
    "number": 6
  },
  {
    "command": "wait",
    "category": 1,
    "args": [
      "25"
    ],
    "number": 13
  },
  {
    "command": "print",
    "category": 1,
    "args": [
      "モニカ",
      "誇\u308A高\u304Dヴァイスフリューゲル\u3092率\u3044\u308B\u2500\u2500"
    ],
    "number": 6
  },
  {
    "command": "touch",
    "category": 1,
    "args": [],
    "number": 10
  },
  {
    "command": "focus",
    "category": 1,
    "args": [
      "105311"
    ],
    "number": 4
  },
  {
    "command": "bust",
    "category": 1,
    "args": [
      "105311",
      "0"
    ],
    "number": 50
  },
  {
    "command": "vo",
    "category": 1,
    "args": [
      "vo_adv_5052101_004"
    ],
    "number": 12
  },
  {
    "command": "face",
    "category": 1,
    "args": [
      "105311",
      "1"
    ],
    "number": 3
  },
  {
    "command": "eye_open",
    "category": 1,
    "args": [
      "True"
    ],
    "number": 56
  },
  {
    "command": "emotion",
    "category": 3,
    "args": [
      "twinkle1_R",
      "105311",
      "-125",
      "465",
      "se_adv_emote_twinkle_01"
    ],
    "number": 59
  },
  {
    "command": "print",
    "category": 1,
    "args": [
      "モニカ",
      "\u2500\u2500提督\u306B\u306A\u308B\u3053\u3068\u3060！"
    ],
    "number": 6
  },
  {
    "command": "touch",
    "category": 1,
    "args": [],
    "number": 10
  },
  {
    "command": "focus",
    "category": 1,
    "args": [
      "105311"
    ],
    "number": 4
  },
  {
    "command": "bust",
    "category": 1,
    "args": [
      "105311",
      "0"
    ],
    "number": 50
  },
  {
    "command": "vo",
    "category": 1,
    "args": [
      "vo_adv_5052101_005"
    ],
    "number": 12
  },
  {
    "command": "face",
    "category": 1,
    "args": [
      "105311",
      "4"
    ],
    "number": 3
  },
  {
    "command": "print",
    "category": 1,
    "args": [
      "モニカ",
      "\u3082\u3061\u308D\u3093、\u305D\u308C\u306F簡単\u306A\u3053\u3068\u3067\u306F\u306A\u3044。"
    ],
    "number": 6
  },
  {
    "command": "wait",
    "category": 1,
    "args": [
      "45"
    ],
    "number": 13
  },
  {
    "command": "print",
    "category": 1,
    "args": [
      "モニカ",
      "\n提督\u306B\u306A\u308B\u305F\u3081\u306E道\u306F"
    ],
    "number": 6
  },
  {
    "command": "wait",
    "category": 1,
    "args": [
      "30"
    ],
    "number": 13
  },
  {
    "command": "print",
    "category": 1,
    "args": [
      "モニカ",
      "\u3064\u3089\u304F、"
    ],
    "number": 6
  },
  {
    "command": "wait",
    "category": 1,
    "args": [
      "20"
    ],
    "number": 13
  },
  {
    "command": "print",
    "category": 1,
    "args": [
      "モニカ",
      "厳\u3057\u3044\u2026\u2026！"
    ],
    "number": 6
  },
  {
    "command": "touch",
    "category": 1,
    "args": [],
    "number": 10
  },
  {
    "command": "focus",
    "category": 1,
    "args": [
      "105311"
    ],
    "number": 4
  },
  {
    "command": "bust",
    "category": 1,
    "args": [
      "105311",
      "0"
    ],
    "number": 50
  },
  {
    "command": "vo",
    "category": 1,
    "args": [
      "vo_adv_5052101_006"
    ],
    "number": 12
  },
  {
    "command": "face",
    "category": 1,
    "args": [
      "105311",
      "1"
    ],
    "number": 3
  },
  {
    "command": "print",
    "category": 1,
    "args": [
      "モニカ",
      "\u3060\u304C私\u306F、"
    ],
    "number": 6
  },
  {
    "command": "wait",
    "category": 1,
    "args": [
      "35"
    ],
    "number": 13
  },
  {
    "command": "print",
    "category": 1,
    "args": [
      "モニカ",
      "\u305D\u306E大\u304D\u306A夢\u3092叶\u3048\u308B\u305F\u3081、"
    ],
    "number": 6
  },
  {
    "command": "wait",
    "category": 1,
    "args": [
      "50"
    ],
    "number": 13
  },
  {
    "command": "print",
    "category": 1,
    "args": [
      "モニカ",
      "\n今日\u3082今日\u3068\u3066"
    ],
    "number": 6
  },
  {
    "command": "wait",
    "category": 1,
    "args": [
      "25"
    ],
    "number": 13
  },
  {
    "command": "print",
    "category": 1,
    "args": [
      "モニカ",
      "活動\u3057\u3066\u3044\u308B\u306E\u3067\u3042\u308B！"
    ],
    "number": 6
  },
  {
    "command": "touch",
    "category": 1,
    "args": [],
    "number": 10
  },
  {
    "command": "focus",
    "category": 1,
    "args": [
      "105311"
    ],
    "number": 4
  },
  {
    "command": "bust",
    "category": 1,
    "args": [
      "105311",
      "0"
    ],
    "number": 50
  },
  {
    "command": "vo",
    "category": 1,
    "args": [
      "vo_adv_5052101_007"
    ],
    "number": 12
  },
  {
    "command": "face",
    "category": 1,
    "args": [
      "105311",
      "3"
    ],
    "number": 3
  },
  {
    "command": "nod",
    "category": 2,
    "args": [
      "105311"
    ],
    "number": 25
  },
  {
    "command": "se",
    "category": 1,
    "args": [
      "se_adv_step_concrete_move_01"
    ],
    "number": 26
  },
  {
    "command": "print",
    "category": 1,
    "args": [
      "モニカ",
      "\u3055\u3041、"
    ],
    "number": 6
  },
  {
    "command": "wait",
    "category": 1,
    "args": [
      "10"
    ],
    "number": 13
  },
  {
    "command": "print",
    "category": 1,
    "args": [
      "モニカ",
      "行\u304F\u305E！"
    ],
    "number": 6
  },
  {
    "command": "wait",
    "category": 1,
    "args": [
      "25"
    ],
    "number": 13
  },
  {
    "command": "print",
    "category": 1,
    "args": [
      "モニカ",
      "\n輝\u304B\u3057\u3044未来\u3078\u3068向\u304B\u3063\u3066！"
    ],
    "number": 6
  },
  {
    "command": "touch",
    "category": 1,
    "args": [],
    "number": 10
  },
  {
    "command": "focus",
    "category": 1,
    "args": [
      "105311"
    ],
    "number": 4
  },
  {
    "command": "bust",
    "category": 1,
    "args": [
      "105311",
      "0"
    ],
    "number": 50
  },
  {
    "command": "vo",
    "category": 1,
    "args": [
      "vo_adv_5052101_008"
    ],
    "number": 12
  },
  {
    "command": "face",
    "category": 1,
    "args": [
      "105311",
      "1"
    ],
    "number": 3
  },
  {
    "command": "print",
    "category": 1,
    "args": [
      "モニカ",
      "提督\u3078\u306E道\u3082、"
    ],
    "number": 6
  },
  {
    "command": "wait",
    "category": 1,
    "args": [
      "30"
    ],
    "number": 13
  },
  {
    "command": "print",
    "category": 1,
    "args": [
      "モニカ",
      "一歩\u304B\u3089\u3060！"
    ],
    "number": 6
  },
  {
    "command": "touch",
    "category": 1,
    "args": [],
    "number": 10
  },
  {
    "command": "bgm",
    "category": 1,
    "args": [
      "stop",
      "2",
      "1"
    ],
    "number": 9
  },
  {
    "command": "window_visible",
    "category": 1,
    "args": [
      "false"
    ],
    "number": 41
  },
  {
    "command": "fadeout",
    "category": 2,
    "args": [
      "105311",
      "30"
    ],
    "number": 19
  },
  {
    "command": "amb_stop",
    "category": 1,
    "args": [
      "2"
    ],
    "number": 61
  },
  {
    "command": "white_out",
    "category": 1,
    "args": [
      "1",
      "1"
    ],
    "number": 29
  },
  {
    "command": "effect",
    "category": 3,
    "args": [
      "0022"
    ],
    "number": 54
  },
  {
    "command": "bg_color",
    "category": 1,
    "args": [
      "255",
      "235",
      "250"
    ],
    "number": 70
  },
  {
    "command": "wait",
    "category": 1,
    "args": [
      "15"
    ],
    "number": 13
  },
  {
    "command": "se",
    "category": 1,
    "args": [
      "se_adv_happy_particle_01"
    ],
    "number": 26
  },
  {
    "command": "white_in",
    "category": 1,
    "args": [],
    "number": 30
  },
  {
    "command": "chara_full",
    "category": 1,
    "args": [
      "101411",
      "R",
      "2"
    ],
    "number": 68
  },
  {
    "command": "chara_full",
    "category": 1,
    "args": [
      "103711",
      "C",
      "2"
    ],
    "number": 68
  },
  {
    "command": "chara_full",
    "category": 1,
    "args": [
      "103811",
      "L",
      "2"
    ],
    "number": 68
  },
  {
    "command": "fadein_all",
    "category": 1,
    "args": [
      "30"
    ],
    "number": 84
  },
  {
    "command": "focus",
    "category": 1,
    "args": [
      "101411:103711:103811"
    ],
    "number": 4
  },
  {
    "command": "window_visible",
    "category": 1,
    "args": [
      "true"
    ],
    "number": 41
  },
  {
    "command": "bgm",
    "category": 1,
    "args": [
      "bgm_M421_WithIntro"
    ],
    "number": 9
  },
  {
    "command": "bust",
    "category": 1,
    "args": [
      "0",
      "0"
    ],
    "number": 50
  },
  {
    "command": "vo",
    "category": 1,
    "args": [
      "vo_adv_5052101_009"
    ],
    "number": 12
  },
  {
    "command": "multi_talk",
    "category": 1,
    "args": [
      "101411:103711:103811"
    ],
    "number": 102
  },
  {
    "command": "face",
    "category": 1,
    "args": [
      "1",
      "1"
    ],
    "number": 3
  },
  {
    "command": "print",
    "category": 1,
    "args": [
      "３人",
      "次回"
    ],
    "number": 6
  },
  {
    "command": "wait",
    "category": 1,
    "args": [
      "25"
    ],
    "number": 13
  },
  {
    "command": "print",
    "category": 1,
    "args": [
      "３人",
      "『魔法提督"
    ],
    "number": 6
  },
  {
    "command": "wait",
    "category": 1,
    "args": [
      "25"
    ],
    "number": 13
  },
  {
    "command": "print",
    "category": 1,
    "args": [
      "３人",
      "ラブリー\u2605モニカ\u3000"
    ],
    "number": 6
  },
  {
    "command": "wait",
    "category": 1,
    "args": [
      "25"
    ],
    "number": 13
  },
  {
    "command": "print",
    "category": 1,
    "args": [
      "３人",
      "レッツゴー！"
    ],
    "number": 6
  },
  {
    "command": "wait",
    "category": 1,
    "args": [
      "20"
    ],
    "number": 13
  },
  {
    "command": "print",
    "category": 1,
    "args": [
      "３人",
      "マジカルカルテット！』"
    ],
    "number": 6
  },
  {
    "command": "touch",
    "category": 1,
    "args": [],
    "number": 10
  },
  {
    "command": "window_visible",
    "category": 1,
    "args": [
      "false"
    ],
    "number": 41
  },
  {
    "command": "fadeout_all",
    "category": 2,
    "args": [
      "30"
    ],
    "number": 45
  },
  {
    "command": "white_out",
    "category": 1,
    "args": [
      "1",
      "1"
    ],
    "number": 29
  },
  {
    "command": "effect_delete",
    "category": 3,
    "args": [
      "0022",
      "30"
    ],
    "number": 55
  },
  {
    "command": "background",
    "category": 1,
    "args": [
      "500010"
    ],
    "number": 5
  },
  {
    "command": "wait",
    "category": 1,
    "args": [
      "15"
    ],
    "number": 13
  },
  {
    "command": "white_in",
    "category": 1,
    "args": [],
    "number": 30
  },
  {
    "command": "amb",
    "category": 1,
    "args": [
      "amb_adv_town_day_01"
    ],
    "number": 51
  },
  {
    "command": "chara_full",
    "category": 1,
    "args": [
      "105311",
      "C",
      "6"
    ],
    "number": 68
  },
  {
    "command": "fadein",
    "category": 2,
    "args": [
      "105311",
      "30"
    ],
    "number": 18
  },
  {
    "command": "window_visible",
    "category": 1,
    "args": [
      "true"
    ],
    "number": 41
  },
  {
    "command": "focus",
    "category": 1,
    "args": [
      "105311"
    ],
    "number": 4
  },
  {
    "command": "bust",
    "category": 1,
    "args": [
      "105311",
      "0"
    ],
    "number": 50
  },
  {
    "command": "vo",
    "category": 1,
    "args": [
      "vo_adv_5052101_010"
    ],
    "number": 12
  },
  {
    "command": "face",
    "category": 1,
    "args": [
      "105311",
      "6"
    ],
    "number": 3
  },
  {
    "command": "emotion",
    "category": 3,
    "args": [
      "question1_R",
      "105311",
      "105",
      "475",
      "se_adv_emote_question_01"
    ],
    "number": 59
  },
  {
    "command": "print",
    "category": 1,
    "args": [
      "モニカ",
      "\u2026\u2026\u3093？"
    ],
    "number": 6
  },
  {
    "command": "wait",
    "category": 1,
    "args": [
      "30"
    ],
    "number": 13
  },
  {
    "command": "print",
    "category": 1,
    "args": [
      "モニカ",
      "\n今\u306A\u306B\u304B、"
    ],
    "number": 6
  },
  {
    "command": "wait",
    "category": 1,
    "args": [
      "30"
    ],
    "number": 13
  },
  {
    "command": "print",
    "category": 1,
    "args": [
      "モニカ",
      "妙\u306A言葉\u304C聞\u3053\u3048\u305F\u3088\u3046\u306A\u2026\u2026？"
    ],
    "number": 6
  },
  {
    "command": "touch",
    "category": 1,
    "args": [],
    "number": 10
  },
  {
    "command": "window_visible",
    "category": 1,
    "args": [
      "FALSE"
    ],
    "number": 41
  },
  {
    "command": "fadeout",
    "category": 2,
    "args": [
      "105311",
      "30"
    ],
    "number": 19
  },
  {
    "command": "bg_pan",
    "category": 1,
    "args": [
      "0",
      "-170"
    ],
    "number": 86
  },
  {
    "command": "bgm",
    "category": 1,
    "args": [
      "stop",
      "1"
    ],
    "number": 9
  },
  {
    "command": "amb_stop",
    "category": 1,
    "args": [
      "1"
    ],
    "number": 61
  },
  {
    "command": "black_out",
    "category": 1,
    "args": [
      "1",
      "1"
    ],
    "number": 27
  },
  {
    "command": "end",
    "category": 1,
    "args": [],
    "number": 58
  }
]